gemgis/__init__.py
gemgis/_version_generated.py
gemgis/download_gemgis_data.py
gemgis/gemgis.py
gemgis/misc.py
gemgis/postprocessing.py
gemgis/raster.py
gemgis/utils.py
gemgis/vector.py
gemgis/visualization.py
gemgis/web.py
GemGIS-1.1.8.dist-info/LICENSE
GemGIS-1.1.8.dist-info/METADATA
GemGIS-1.1.8.dist-info/WHEEL
GemGIS-1.1.8.dist-info/top_level.txt
GemGIS-1.1.8.dist-info/RECORD
