Metadata-Version: 2.1
Name: GemGIS
Version: 1.1.8
Summary: Spatial data processing for geomodeling
Maintainer: Arthur Endlein Correia, Marius Pischke, Florian Wellmann
Maintainer-email: Alexander Jüstel <alexander.juestel@rwth-aachen.de>
License:                    GNU LESSER GENERAL PUBLIC LICENSE
Project-URL: Documentation, https://gemgis.readthedocs.io/
Project-URL: Home, https://gemgis.readthedocs.io/
Project-URL: Bug Tracker, https://github.com/cgre-aachen/gemgis/issues
Project-URL: Repository, https://github.com/cgre-aachen/gemgis
Project-URL: Source Code, https://github.com/cgre-aachen/gemgis
Keywords: dataprocessing,modeling,geospatial,geographic-data,spatial-data,rasterdata,vectordata,geographic,geomodeling
Classifier: Development Status :: 5 - Production/Stable
Classifier: Intended Audience :: Science/Research
Classifier: Topic :: Scientific/Engineering :: Information Analysis
Classifier: Programming Language :: Python :: 3.8
Classifier: Programming Language :: Python :: 3.9
Classifier: Programming Language :: Python :: 3.10
Classifier: Programming Language :: Python :: 3.11
Classifier: License :: OSI Approved :: GNU General Public License v3 (GPLv3)
Classifier: Operating System :: OS Independent
Requires-Python: >=3.8
License-File: LICENSE
Requires-Dist: geopandas
Requires-Dist: rasterio
Requires-Dist: pyvista
Provides-Extra: optionals
Requires-Dist: scipy; extra == "optionals"
Requires-Dist: pypdf; extra == "optionals"
Requires-Dist: tqdm; extra == "optionals"
Requires-Dist: gempy; extra == "optionals"
Requires-Dist: pvgeo; extra == "optionals"
Requires-Dist: xml; extra == "optionals"
Requires-Dist: scikit-image; extra == "optionals"
Requires-Dist: xmltodict; extra == "optionals"
Requires-Dist: geopy; extra == "optionals"
Requires-Dist: scikit-learn; extra == "optionals"
Requires-Dist: py7zr; extra == "optionals"
Requires-Dist: segysak; extra == "optionals"
Requires-Dist: rioxarray; extra == "optionals"
Requires-Dist: tqdm; extra == "optionals"
Requires-Dist: mplstereonet; extra == "optionals"
Requires-Dist: xarray; extra == "optionals"
Requires-Dist: owslib; extra == "optionals"
Requires-Dist: requests; extra == "optionals"
Requires-Dist: urllib; extra == "optionals"
Provides-Extra: build
Requires-Dist: setuptools; extra == "build"
Requires-Dist: wheel; extra == "build"
Requires-Dist: twine; extra == "build"
Requires-Dist: build; extra == "build"
Provides-Extra: docs
Requires-Dist: sphinx; extra == "docs"
Requires-Dist: nbsphinx; extra == "docs"
Requires-Dist: sphinx_markdown_tables; extra == "docs"
Requires-Dist: sphinx_gallery; extra == "docs"
Requires-Dist: sphinx_rtd_theme; extra == "docs"
Requires-Dist: sphinx_book_theme==0.3.3; extra == "docs"
Requires-Dist: sphinx_copybutton; extra == "docs"
Requires-Dist: sphinx_automodapi; extra == "docs"
Requires-Dist: sphinx_numfig; extra == "docs"
Requires-Dist: numpydoc; extra == "docs"
Provides-Extra: tests
Requires-Dist: pytest; extra == "tests"
Requires-Dist: pytest-cov; extra == "tests"
